logto/LogtoClient.py
logto/LogtoClient_test.py
logto/LogtoException.py
logto/OidcCore.py
logto/OidcCore_test.py
logto/Storage.py
logto/__init__.py
logto/models/oidc.py
logto/models/response.py
logto/utilities/__init__.py
logto/utilities/__init__test.py
logto/utilities/test.py
logto-0.2.0.dist-info/METADATA
logto-0.2.0.dist-info/WHEEL
logto-0.2.0.dist-info/RECORD
