Metadata-Version: 2.1
Name: logto
Version: 0.2.0
Summary: Logto Python SDK.
Home-page: https://logto.io/
License: MIT
Keywords: logto,auth,user,authentication,authorization
Author: Silverhand Inc.
Author-email: contact@silverhand.io
Requires-Python: >=3.8,<4.0
Classifier: License :: OSI Approved :: MIT License
Classifier: Programming Language :: Python :: 3
Classifier: Programming Language :: Python :: 3.8
Classifier: Programming Language :: Python :: 3.9
Classifier: Programming Language :: Python :: 3.10
Classifier: Programming Language :: Python :: 3.11
Classifier: Programming Language :: Python :: 3.12
Requires-Dist: aiohttp (>=3.8.5,<4.0.0)
Requires-Dist: pydantic (>=2.1.1,<3.0.0)
Requires-Dist: pyjwt[crypto] (>=2.8.0,<3.0.0)
Project-URL: Documentation, https://github.com/logto-io/python/tree/master/docs
Project-URL: Repository, https://github.com/logto-io/python
